{
   "image_filename": "10270_JeepGrand Cherokee2015_2400.png",
   "complete": null,
   "labels": [
      {
         "label_type": "polygon",
         "label_class": "window",
         "source": "manual",
         "anno_data": {
            "good_quality": true,
            "visibility": "mostly"
         },
         "regions": [
            [
               {
                  "x": 1585.1329136194195,
                  "y": 662.1964152343269
               },
               {
                  "x": 1573.6140618948207,
                  "y": 612.2813910943992
               },
               {
                  "x": 1561.4552739632998,
                  "y": 571.9654100583036
               },
               {
                  "x": 1550.1649129102775,
                  "y": 541.6597040738749
               },
               {
                  "x": 1548.360460299927,
                  "y": 537.3567786184236
               },
               {
                  "x": 1547.1550356203684,
                  "y": 534.2929908912124
               },
               {
                  "x": 1546.683583950556,
                  "y": 533.8215392214001
               },
               {
                  "x": 1546.3995735463113,
                  "y": 532.7615979628804
               },
               {
                  "x": 1545.9076530962814,
                  "y": 532.2696775128504
               },
               {
                  "x": 1545.3396322877918,
                  "y": 530.1497949958114
               },
               {
                  "x": 1544.3557913877316,
                  "y": 529.1659540957511
               },
               {
                  "x": 1543.7877705792423,
                  "y": 527.0460715787121
               },
               {
                  "x": 1543.5798605334567,
                  "y": 526.8381615329265
               },
               {
                  "x": 1543.011839724967,
                  "y": 524.7182790158873
               },
               {
                  "x": 1542.38246134936,
                  "y": 524.0889006402803
               },
               {
                  "x": 1541.4344570342619,
                  "y": 521.5193099967246
               },
               {
                  "x": 1540.6882528627514,
                  "y": 518.7344381158271
               },
               {
                  "x": 1540.7295617339312,
                  "y": 518.5563467534772
               },
               {
                  "x": 1540.4761371163572,
                  "y": 518.3029221359031
               },
               {
                  "x": 1540.1921267121124,
                  "y": 517.2429808773834
               },
               {
                  "x": 1539.7002062620825,
                  "y": 516.7510604273534
               },
               {
                  "x": 1539.4161958578377,
                  "y": 515.6911191688339
               },
               {
                  "x": 1539.2071135457124,
                  "y": 515.4820368567088
               },
               {
                  "x": 1534.668864254538,
                  "y": 503.1809927253672
               },
               {
                  "x": 1534.7598752419563,
                  "y": 502.7886249294148
               },
               {
                  "x": 1532.7428121375744,
                  "y": 497.6619228724442
               },
               {
                  "x": 1532.3517332974425,
                  "y": 496.9003482890293
               },
               {
                  "x": 1529.2239257145243,
                  "y": 488.4223435248037
               },
               {
                  "x": 1528.6736204147182,
                  "y": 489.73770741214514
               },
               {
                  "x": 1528.1785912033479,
                  "y": 488.77370315842404
               },
               {
                  "x": 1516.6597394787493,
                  "y": 487.4938307445797
               },
               {
                  "x": 1510.90031361645,
                  "y": 484.93408591689115
               },
               {
                  "x": 1497.4616532710847,
                  "y": 474.69510660613673
               },
               {
                  "x": 1489.1424825810968,
                  "y": 470.21555315768165
               },
               {
                  "x": 1466.7447153388216,
                  "y": 467.0158721230709
               },
               {
                  "x": 1412.990073957361,
                  "y": 464.4561272953823
               },
               {
                  "x": 1367.554603265888,
                  "y": 462.53631867461587
               },
               {
                  "x": 1303.560982573673,
                  "y": 462.53631867461587
               },
               {
                  "x": 1291.4021946421522,
                  "y": 461.8963824676937
               },
               {
                  "x": 1264.5248739514218,
                  "y": 483.01427729612465
               },
               {
                  "x": 1138.4574411877581,
                  "y": 483.01427729612465
               },
               {
                  "x": 1110.9401842901057,
                  "y": 461.8963824676937
               },
               {
                  "x": 1054.6257980809564,
                  "y": 463.176254881538
               },
               {
                  "x": 1031.588094631759,
                  "y": 463.176254881538
               },
               {
                  "x": 1005.3507101479508,
                  "y": 465.7359997092266
               },
               {
                  "x": 979.7532618710648,
                  "y": 466.37593591614876
               },
               {
                  "x": 959.915239456478,
                  "y": 469.5756169507595
               },
               {
                  "x": 937.5174722142028,
                  "y": 472.77529798537023
               },
               {
                  "x": 933.259512458227,
                  "y": 472.77529798537023
               },
               {
                  "x": 932.9184291103705,
                  "y": 473.1163813332267
               },
               {
                  "x": 927.9184291103705,
                  "y": 474.4561272953823
               },
               {
                  "x": 926.232853398139,
                  "y": 474.00447864450837
               },
               {
                  "x": 922.1590032480711,
                  "y": 475.09606350230445
               },
               {
                  "x": 921.8197907459141,
                  "y": 475.0154848284677
               },
               {
                  "x": 921.519067041149,
                  "y": 475.09606350230445
               },
               {
                  "x": 921.179854538992,
                  "y": 475.0154848284677
               },
               {
                  "x": 920.8791308342269,
                  "y": 475.09606350230445
               },
               {
                  "x": 920.5399183320699,
                  "y": 475.0154848284677
               },
               {
                  "x": 920.2391946273048,
                  "y": 475.09606350230445
               },
               {
                  "x": 919.8999821251477,
                  "y": 475.0154848284677
               },
               {
                  "x": 919.5992584203826,
                  "y": 475.09606350230445
               },
               {
                  "x": 919.2600459182256,
                  "y": 475.0154848284677
               },
               {
                  "x": 918.9593222134605,
                  "y": 475.09606350230445
               },
               {
                  "x": 918.1467532922873,
                  "y": 474.87833631608146
               },
               {
                  "x": 908.7203429027061,
                  "y": 477.89478764074744
               },
               {
                  "x": 894.0018101434965,
                  "y": 484.93408591689115
               },
               {
                  "x": 885.0427032465865,
                  "y": 490.05357557226836
               },
               {
                  "x": 879.2832773842871,
                  "y": 490.6935117791905
               },
               {
                  "x": 867.1244894527663,
                  "y": 519.4906410906873
               },
               {
                  "x": 846.6465308312575,
                  "y": 583.4842617829023
               },
               {
                  "x": 831.9279980720479,
                  "y": 629.5596686812972
               },
               {
                  "x": 824.8886997959042,
                  "y": 663.4762876481711
               },
               {
                  "x": 824.8886997959042,
                  "y": 664.1162238550934
               },
               {
                  "x": 826.8085084166707,
                  "y": 664.1162238550934
               },
               {
                  "x": 1197.7482119810443,
                  "y": 663.1771359979683
               },
               {
                  "x": 1200.8992597628403,
                  "y": 664.0214567064124
               },
               {
                  "x": 1204.1104191405032,
                  "y": 663.1610291444001
               }
            ]
         ],
         "object_id": "c51c8ca5-4a5c-4b42-8129-1fc1ed7af3a6__10"
      },
      {
         "label_type": "polygon",
         "label_class": "null",
         "source": "manual",
         "anno_data": {},
         "regions": [
            [
               {
                  "x": 1291.4021946421522,
                  "y": 842.6584255863734
               },
               {
                  "x": 1291.4021946421522,
                  "y": 755.6271014449609
               },
               {
                  "x": 1114.7798015316387,
                  "y": 754.9871652380388
               },
               {
                  "x": 1114.8325256654207,
                  "y": 757.3597512582267
               },
               {
                  "x": 1114.13168187218,
                  "y": 755.2572198785049
               },
               {
                  "x": 1115.215407839025,
                  "y": 840.8715712592423
               },
               {
                  "x": 1116.6889859696394,
                  "y": 840.9004649480778
               },
               {
                  "x": 1116.699610152405,
                  "y": 841.3785531725291
               }
            ]
         ],
         "object_id": "f1b9b711-6dfb-484e-9bbb-9407b1c3ebf8__4"
      }
   ]
}